Metadata-Version: 1.0
Name: centre-config
Version: 0.1.1
Summary: Pull centre specific data.
Home-page: UNKNOWN
Author: Simon Biggs
Author-email: mail@simonbiggs.net
License: AGPL3+
Platform: UNKNOWN
